arpit/__init__.py
arpit/desc.py
arpit/error.py
arpit/main.py
arpit/music.py
arpit/utils.py
arpit/video.py
arpit/assets/audio/easter_audio.mp3
arpit/assets/audio/error_audio.mp3
arpit/assets/audio/no_audio.mp3
arpit/assets/audio/sunday.mp3
arpit/assets/audio/yes_audio.mp3
arpit/assets/misc/data.json
arpit/assets/misc/error_image.png
arpit/assets/video/easter_video.mp4
arpit-2.0.2.dist-info/LICENSE
arpit-2.0.2.dist-info/METADATA
arpit-2.0.2.dist-info/WHEEL
arpit-2.0.2.dist-info/entry_points.txt
arpit-2.0.2.dist-info/top_level.txt
arpit-2.0.2.dist-info/RECORD
